Tool.py
cxrtestlib/__init__.py
cxrtestlib/cxrlibone.py
xinxu131813-1.1.0.dist-info/LICENSE.txt
xinxu131813-1.1.0.dist-info/METADATA
xinxu131813-1.1.0.dist-info/WHEEL
xinxu131813-1.1.0.dist-info/top_level.txt
xinxu131813-1.1.0.dist-info/RECORD
