Metadata-Version: 2.1
Name: xinxu131813
Version: 1.1.0
Summary: thie is nb lib
Home-page: UNKNOWN
Author: Cxr
Author-email: 1318304701@qq.com
License: MIT
Platform: UNKNOWN
License-File: LICENSE.txt
